README.rst
setup.py
f3/__init__.py
f3/files.py
f3/obs_info.txt
f3/photometry.py
f3.egg-info/PKG-INFO
f3.egg-info/SOURCES.txt
f3.egg-info/dependency_links.txt
f3.egg-info/requires.txt
f3.egg-info/top_level.txt