Metadata-Version: 1.1
Name: f3
Version: 1.0
Summary: Photometry for Kepler Full Frame Images
Home-page: http://github.com/benmontet/f3
Author: Ben Montet
Author-email: bmontet@uchicago.edu
License: MIT
Platform: UNKNOWN
Classifier: Development Status :: 5 - Production/Stable
Classifier: Intended Audience :: Science/Research
Classifier: License :: OSI Approved :: MIT License
Classifier: Operating System :: OS Independent
Classifier: Programming Language :: Python :: 2.7
